blade/__init__.py
blade/__main__.py
blade/checker.py
blade/elaborator.py
blade/parser.py
blade/project.py
blade/checkers/__init__.py
blade/checkers/apertures.py
blade/checkers/common.py
blade/elaborate/__init__.py
blade/elaborate/address_map.py
blade/elaborate/common.py
blade/elaborate/define.py
blade/elaborate/instruction.py
blade/elaborate/interconnect.py
blade/elaborate/module.py
blade/elaborate/register_interrupt.py
blade/elaborate/register_setclear.py
blade/elaborate/registers.py
blade/preprocessor/__init__.py
blade/preprocessor/block.py
blade/preprocessor/common.py
blade/preprocessor/file.py
blade/preprocessor/for_block.py
blade/preprocessor/if_block.py
blade/preprocessor/line.py
blade/preprocessor/scope.py
blade/preprocessor/statement.py
blade/reporting/__init__.py
blade/reporting/render.py
blade/reporting/templates/blocks.html.mk
blade/reporting/templates/report.html.mk
blade/schema/__init__.py
blade/schema/ph_config.py
blade/schema/ph_connect.py
blade/schema/ph_const.py
blade/schema/ph_def.py
blade/schema/ph_define.py
blade/schema/ph_enum.py
blade/schema/ph_field.py
blade/schema/ph_group.py
blade/schema/ph_his.py
blade/schema/ph_his_ref.py
blade/schema/ph_initiator.py
blade/schema/ph_inst.py
blade/schema/ph_macro.py
blade/schema/ph_mod.py
blade/schema/ph_mod_inst.py
blade/schema/ph_point.py
blade/schema/ph_port.py
blade/schema/ph_reg.py
blade/schema/ph_register.py
blade/schema/ph_tag_base.py
blade/schema/ph_target.py
blade/schema/schema_helpers.py
blu_blade-1.0.data/data/LICENSE
blu_blade-1.0.data/data/blocks.html.mk
blu_blade-1.0.data/data/report.html.mk
blu_blade-1.0.dist-info/LICENSE
blu_blade-1.0.dist-info/METADATA
blu_blade-1.0.dist-info/WHEEL
blu_blade-1.0.dist-info/entry_points.txt
blu_blade-1.0.dist-info/top_level.txt
blu_blade-1.0.dist-info/RECORD
