Metadata-Version: 2.1
Name: blu-blade
Version: 1.0
Summary: Hardware Design, Exploration, and Code Generation for SoC Designers
Home-page: https://www.bluwireless.com
Author: Blu Wireless Ltd
License: GNU General Public License v3.0
Project-URL: Source, https://github.com/bluwireless/blade
Project-URL: Tracker, https://github.com/bluwireless/blade/issues
Platform: UNKNOWN
Requires-Dist: designformat
Requires-Dist: pyyaml
Requires-Dist: mako
Requires-Dist: tqdm
Provides-Extra: documentation
Requires-Dist: sphinx ; extra == 'documentation'
Requires-Dist: recommonmark ; extra == 'documentation'
Requires-Dist: sphinx-markdown-tables ; extra == 'documentation'
Requires-Dist: sphinx-rtd-theme ; extra == 'documentation'
